[{"Index":0,"SearchText":"Faster Cast Recovery","FormattedText":"/c[blue]{0}{1}","Min1":1,"Max1":1,"Min2":-1,"Max2":99,"ItemLayer":162,"IsNew":false},{"Index":1,"SearchText":"Faster Cast Recovery","FormattedText":"/c[yellow]{0}{1}","Min1":2,"Max1":2,"Min2":-1,"Max2":99,"ItemLayer":162,"IsNew":false},{"Index":2,"SearchText":"Faster Cast Recovery","FormattedText":"/c[orange]{0}{1}","Min1":3,"Max1":3,"Min2":-1,"Max2":99,"ItemLayer":162,"IsNew":false},{"Index":3,"SearchText":"Faster Cast Recovery","FormattedText":"/c[red]{0}{1}","Min1":4,"Max1":99,"Min2":-1,"Max2":99,"ItemLayer":162,"IsNew":false}]